{
    "Mechanical System": {
        "Name": "Elastic_Pendulum",
        "Path": "C:\\Users\\E1243377\\Python\\N_Body\\Mechanical_Systems_Library\\Elastic_Pendulum\\",
        "Dimensions": 2,
        "Particles": 1,
        "Parameters": {
            "g": 9.81,
            "m1": 1.0,
            "k": 9.81,
            "r0": 1.0
        },
        "Degrees of Freedom": {
            "r": "r",
            "theta": "theta"
        },
        "Cartesian Coordinates": {
            "x1": "r * sin(theta)",
            "y1": "-r * cos(theta)"
        },
        "Potential Energy": {
            "V1": "m1 * g * y1 + 1/2 * k * (r - r0)**2"
        },
        "Friction Coefficients": {
            "r_friction": 0.0,
            "theta_friction": 0.0
        },
        "Driving Force Coefficients": {
            "A_r_drive": 0.0,
            "w_r_drive": 0.0,
            "phi_r_drive": 0.0,
            "A_theta_drive": 0.0,
            "w_theta_drive": 0.0,
            "phi_theta_drive": 0.0
        },
        "Notes": "This system consists of a pendulum in which the string connected to the bob is replaced by a spring.\nIt is important to notice that if r0 is the equilibrium position of the spring, because of gravity, the equilibrium position will be shifted downward\nThe new equilibrium position for theta = 0 is obtained by equating the magnitudes of the elastic force and the force of gravity:\n|Fe| = k * (r_eq - r0)\n|Fg| = m * g\nr_eq = r0 + m * g / k\nThe displacement of the equilibrium position is equal to m * g / k"
    },
    "Initial Conditions": {
        "r(0)": 3.4,
        "drdt(0)": 0.0,
        "theta(0)": 1.0,
        "dthetadt(0)": 0.0
    },
    "Integration Parameters": {
        "t_initial": 0.0,
        "t_final": 10.0,
        "iterations": 100
    },
    "Equations of Motion": {},
    "Output": {}
}